gistfinder/__init__.py
gistfinder/config.py
gistfinder/console.py
gistfinder/loader.py
gistfinder/sync.py
gistfinder/utils.py
gistfinder/version.py
gistfinder/tests/__init__.py
gistfinder/tests/tests.py
gistfinder-0.2.4.dist-info/LICENSE
gistfinder-0.2.4.dist-info/METADATA
gistfinder-0.2.4.dist-info/WHEEL
gistfinder-0.2.4.dist-info/entry_points.txt
gistfinder-0.2.4.dist-info/top_level.txt
gistfinder-0.2.4.dist-info/RECORD
