Metadata-Version: 2.1
Name: gistfinder
Version: 0.2.4
Summary: A CLI tool for searching your gists
Home-page: https://github.com/robdmc/gistfinder
Author: Rob deCarvalho
Author-email: unlisted@unlisted.net
License: MIT
Platform: UNKNOWN
Classifier: Programming Language :: Python :: 2.7
Classifier: Programming Language :: Python :: 3.4
Classifier: Programming Language :: Python :: 3.5
Classifier: Intended Audience :: Developers
Classifier: License :: OSI Approved :: MIT License
Classifier: Operating System :: OS Independent
Requires-Dist: Pygments
Requires-Dist: click
Requires-Dist: dataset
Requires-Dist: fuzzywuzzy
Requires-Dist: prompt-toolkit
Requires-Dist: python-Levenshtein
Requires-Dist: pytz
Requires-Dist: requests
Requires-Dist: tqdm
Provides-Extra: dev
Requires-Dist: coverage ; extra == 'dev'
Requires-Dist: flake8 ; extra == 'dev'
Requires-Dist: mock ; extra == 'dev'
Requires-Dist: nose ; extra == 'dev'
Requires-Dist: wheel ; extra == 'dev'
Requires-Dist: Sphinx ; extra == 'dev'
Requires-Dist: sphinx-rtd-theme ; extra == 'dev'
